allianceauth_pve/__init__.py
allianceauth_pve/actions.py
allianceauth_pve/admin.py
allianceauth_pve/apps.py
allianceauth_pve/auth_hooks.py
allianceauth_pve/forms.py
allianceauth_pve/models.py
allianceauth_pve/urls.py
allianceauth_pve/views.py
allianceauth_pve/locale/en/LC_MESSAGES/django.mo
allianceauth_pve/locale/en/LC_MESSAGES/django.po
allianceauth_pve/locale/it_IT/LC_MESSAGES/django.mo
allianceauth_pve/locale/it_IT/LC_MESSAGES/django.po
allianceauth_pve/migrations/0001_initial.py
allianceauth_pve/migrations/0002_auto_20220409_1358.py
allianceauth_pve/migrations/0003_auto_20220411_1104.py
allianceauth_pve/migrations/0004_auto_20220411_2152.py
allianceauth_pve/migrations/0005_rename_character_entrycharacter_user.py
allianceauth_pve/migrations/0006_auto_20220416_1534.py
allianceauth_pve/migrations/0007_alter_rotation_tax_rate.py
allianceauth_pve/migrations/0008_auto_20220424_1435.py
allianceauth_pve/migrations/0009_pvebutton_rotation_entry_buttons.py
allianceauth_pve/migrations/0010_rolesetup_generalrole_rotation_roles_setups.py
allianceauth_pve/migrations/0011_entryrole_unique_role_name_per_entry_and_more.py
allianceauth_pve/migrations/0012_alter_entry_options_and_more.py
allianceauth_pve/migrations/0013_alter_general_options_alter_rotation_entry_buttons_and_more.py
allianceauth_pve/migrations/0014_alter_rotation_priority.py
allianceauth_pve/migrations/0015_alter_entry_estimated_total_alter_pvebutton_amount_and_more.py
allianceauth_pve/migrations/0016_remove_entrycharacter_actual_share_total_and_more.py
allianceauth_pve/migrations/0017_fundingproject_alter_general_options_and_more.py
allianceauth_pve/migrations/0018_fundingproject_created_at.py
allianceauth_pve/migrations/0019_fundingproject_completed_at.py
allianceauth_pve/migrations/0020_alter_entrycharacter_user_and_more.py
allianceauth_pve/migrations/0021_rotationpreset.py
allianceauth_pve/migrations/__init__.py
allianceauth_pve/static/allianceauth_pve/css/copy_text.css
allianceauth_pve-1.17.0.dist-info/LICENSE
allianceauth_pve-1.17.0.dist-info/WHEEL
allianceauth_pve-1.17.0.dist-info/METADATA
allianceauth_pve-1.17.0.dist-info/RECORD
