Metadata-Version: 2.3
Name: allianceauth-pve
Version: 1.17.0
Summary: PvE tool for AllianceAuth
Keywords: allianceauth,eveonline,allianceauth_pve
Author-email: Matteo Ghia <matteo.ghia@yahoo.it>
Requires-Python: ~=3.9
Classifier: Environment :: Web Environment
Classifier: Framework :: Django
Classifier: Framework :: Django :: 4
Classifier: Framework :: Django :: 4.2
Classifier: Operating System :: POSIX :: Linux
Classifier: Development Status :: 5 - Production/Stable
Classifier: Intended Audience :: Developers
Classifier: License :: OSI Approved :: GNU General Public License v3 (GPLv3)
Classifier: Natural Language :: English
Classifier: Programming Language :: Python :: 3
Classifier: Programming Language :: Python :: 3.9
Classifier: Programming Language :: Python :: 3.10
Classifier: Programming Language :: Python :: 3.11
Classifier: Programming Language :: Python :: 3.12
Classifier: Programming Language :: Python :: 3.13
Classifier: Topic :: Internet :: WWW/HTTP
Classifier: Topic :: Internet :: WWW/HTTP :: Dynamic Content
Requires-Dist: allianceauth~=4.0
Project-URL: Changelog, https://github.com/Maestro-Zacht/allianceauth-pve/releases
Project-URL: Homepage, https://github.com/Maestro-Zacht/allianceauth-pve
Project-URL: Source, https://github.com/Maestro-Zacht/allianceauth-pve
Project-URL: Tracker, https://github.com/Maestro-Zacht/allianceauth-pve/issues
